ez_agent/__init__.py
ez_agent/py.typed
ez_agent/types.py
ez_agent/agent/agent_async.py
ez_agent/agent/base_tool.py
ez_agent/agent/function_tool.py
ez_agent/agent/mcp_tool.py
ez_agent/gui_agent/__init__.py
ez_agent/gui_agent/action_parser.py
ez_agent/gui_agent/gui_agent.py
ez_agent/gui_agent/screenshot.py
ez_agent/prefabs/__init__.py
ez_agent/prefabs/function_tools.py
ez_agent-0.2.3.dist-info/licenses/LICENSE
ez_agent-0.2.3.dist-info/METADATA
ez_agent-0.2.3.dist-info/WHEEL
ez_agent-0.2.3.dist-info/top_level.txt
ez_agent-0.2.3.dist-info/RECORD
