Metadata-Version: 2.4
Name: ez_agent
Version: 0.2.3
Summary: 基于 volcengine-python-sdk 的简单 AI Agent 框架
Author-email: captainSuo <captainsuo@outlook.com>
Project-URL: Homepage, https://github.com/captainSuo/ez-agent
Classifier: Programming Language :: Python :: 3.13
Classifier: License :: OSI Approved :: MIT License
Requires-Python: >=3.13
License-File: LICENSE
Requires-Dist: mcp[cli]>=1.9.2
Requires-Dist: volcengine-python-sdk[ark]>=4.0.31
Provides-Extra: gui
Requires-Dist: pillow>=11.3.0; extra == "gui"
Requires-Dist: pyautogui>=0.9.54; extra == "gui"
Dynamic: license-file
